{
  "display_id": "6820526234343197957",
  "extractor": "generic",
  "protocol": "https",
  "_filename": "World Health Organization (WHO) on TikTok-6820526234343197957.unknown_video",
  "format": "0 - unknown",
  "requested_subtitles": null,
  "playlist_uploader": null,
  "format_id": "0",
  "playlist_index": 1,
  "subtitles": {},
  "playlist_title": "World Health Organization (WHO) on TikTok",
  "playlist": "World Health Organization (WHO) on TikTok",
  "title": "World Health Organization (WHO) on TikTok",
  "url": "https://v19.muscdn.com/edeccd36bd1ad268ea0eb4b20c867bdf/5eac3dd0/video/tos/useast2a/tos-useast2a-ve-0068c003/2048f65253884c74b39bc60861207c98/?a=1233&br=1236&bt=618&cr=0&cs=0&dr=0&ds=3&er=&l=2020050109183001011522806309253EDE&lr=tiktok_m&qs=0&rc=M2ptcnduM2VwdDMzODczM0ApZzdlNzVpZTw2N2lpaTgzOWdxZWxvX19yLWdfLS1iMTZzc2EvYmFiLS41YS4vXjM1XzI6Yw==&vl=&vr=",
  "extractor_key": "Generic",
  "vcodec": null,
  "http_headers": {
    "Accept-Language": "en-us,en;q=0.5",
    "Accept-Encoding": "gzip, deflate",
    "Accept": "text/html,application/xhtml+xml,application/xml;q=0.9,*/*;q=0.8",
    "User-Agent": "Mozilla/5.0 (Windows NT 10.0; Win64; x64) AppleWebKit/537.36 (KHTML, like Gecko) Chrome/69.0.3497.36 Safari/537.36",
    "Accept-Charset": "ISO-8859-1,utf-8;q=0.7,*;q=0.7",
    "Referer": "https://www.tiktok.com/@who/video/6820526234343197957"
  },
  "id": "6820526234343197957",
  "playlist_id": "6820526234343197957",
  "ext": "unknown_video",
  "n_entries": 1,
  "webpage_url": "https://www.tiktok.com/@who/video/6820526234343197957",
  "formats": [
    {
      "protocol": "https",
      "format": "0 - unknown",
      "url": "https://v19.muscdn.com/edeccd36bd1ad268ea0eb4b20c867bdf/5eac3dd0/video/tos/useast2a/tos-useast2a-ve-0068c003/2048f65253884c74b39bc60861207c98/?a=1233&br=1236&bt=618&cr=0&cs=0&dr=0&ds=3&er=&l=2020050109183001011522806309253EDE&lr=tiktok_m&qs=0&rc=M2ptcnduM2VwdDMzODczM0ApZzdlNzVpZTw2N2lpaTgzOWdxZWxvX19yLWdfLS1iMTZzc2EvYmFiLS41YS4vXjM1XzI6Yw==&vl=&vr=",
      "vcodec": null,
      "http_headers": {
        "Accept-Charset": "ISO-8859-1,utf-8;q=0.7,*;q=0.7",
        "Accept-Language": "en-us,en;q=0.5",
        "Accept-Encoding": "gzip, deflate",
        "Referer": "https://www.tiktok.com/@who/video/6820526234343197957",
        "Accept": "text/html,application/xhtml+xml,application/xml;q=0.9,*/*;q=0.8",
        "User-Agent": "Mozilla/5.0 (Windows NT 10.0; Win64; x64) AppleWebKit/537.36 (KHTML, like Gecko) Chrome/69.0.3497.36 Safari/537.36"
      },
      "ext": "unknown_video",
      "format_id": "0"
    }
  ],
  "playlist_uploader_id": null,
  "fulltitle": "World Health Organization (WHO) on TikTok",
  "thumbnail": null,
  "webpage_url_basename": "6820526234343197957"
}
